small_small_hr/__init__.py
small_small_hr/admin.py
small_small_hr/apps.py
small_small_hr/constants.py
small_small_hr/emails.py
small_small_hr/forms.py
small_small_hr/managers.py
small_small_hr/models.py
small_small_hr/reviews.py
small_small_hr/serializers.py
small_small_hr/settings.py
small_small_hr/signals.py
small_small_hr/utils.py
small_small_hr/views.py
small_small_hr/migrations/0001_initial.py
small_small_hr/migrations/0002_auto_20180722_1808.py
small_small_hr/migrations/0003_staffdocument_public.py
small_small_hr/migrations/0004_auto_20180725_2127.py
small_small_hr/migrations/0005_auto_20181115_2112.py
small_small_hr/migrations/0006_auto_20181209_0108.py
small_small_hr/migrations/0007_auto_20190625_2111.py
small_small_hr/migrations/0008_auto_20200607_1537.py
small_small_hr/migrations/0009_auto_20200607_2244.py
small_small_hr/migrations/0010_auto_20200626_1313.py
small_small_hr/migrations/0011_auto_20220131_1640.py
small_small_hr/migrations/__init__.py
small_small_hr/templates/small_small_hr/email/leave_application_email_body.html
small_small_hr/templates/small_small_hr/email/leave_application_email_body.txt
small_small_hr/templates/small_small_hr/email/leave_application_email_subject.txt
small_small_hr/templates/small_small_hr/email/leave_completed_email_body.html
small_small_hr/templates/small_small_hr/email/leave_completed_email_body.txt
small_small_hr/templates/small_small_hr/email/leave_completed_email_subject.txt
small_small_hr/templates/small_small_hr/email/overtime_application_email_body.html
small_small_hr/templates/small_small_hr/email/overtime_application_email_body.txt
small_small_hr/templates/small_small_hr/email/overtime_application_email_subject.txt
small_small_hr/templates/small_small_hr/email/overtime_completed_email_body.html
small_small_hr/templates/small_small_hr/email/overtime_completed_email_body.txt
small_small_hr/templates/small_small_hr/email/overtime_completed_email_subject.txt
small_small_hr/templatetags/__init__.py
small_small_hr-0.4.2.dist-info/LICENSE
small_small_hr-0.4.2.dist-info/METADATA
small_small_hr-0.4.2.dist-info/WHEEL
small_small_hr-0.4.2.dist-info/top_level.txt
small_small_hr-0.4.2.dist-info/RECORD
