Metadata-Version: 2.1
Name: small-small-hr
Version: 0.4.2
Summary: Minimal human resource management app for Django
Home-page: https://github.com/moshthepitt/small-small-hr
Author: Kelvin Jayanoris
Author-email: kelvin@jayanoris.com
License: MIT
Platform: UNKNOWN
Classifier: Programming Language :: Python
Classifier: Programming Language :: Python :: 3.6
Classifier: Programming Language :: Python :: 3.7
Classifier: Programming Language :: Python :: 3.8
Classifier: Framework :: Django
Classifier: Framework :: Django :: 2.2
Classifier: Framework :: Django :: 3.0
Classifier: Framework :: Django :: 3.1
License-File: LICENSE
Requires-Dist: Django (>=2.2)
Requires-Dist: voluptuous
Requires-Dist: psycopg2-binary
Requires-Dist: sorl-thumbnail
Requires-Dist: django-private-storage
Requires-Dist: django-model-reviews
Requires-Dist: phonenumberslite
Requires-Dist: django-phonenumber-field
Requires-Dist: django-crispy-forms
Requires-Dist: djangorestframework
Requires-Dist: Pillow
Requires-Dist: django-mptt
